Workbook

Sheet Dashboard
B2: MC2 ESTIMATING - TPO MEMBRANE
B4: PROJECT INFORMATION
B5: Project Name:
B6: Address:
B7: City, State ZIP:
B8: Client:
B9: Phone:
B10: Email:
B11: Date: | C11: =TODAY()
B12: Estimator:
B14: ESTIMATE SUMMARY
B15: Total Roof Squares: | C15: ='Material Takeoff'!C9
B16: Materials: | C16: =Recap!C14
B17: Material Tax: | C17: =Recap!C15
B18: Labor + Burden: | C18: =Recap!C16
B19: Subs/Equipment: | C19: =Recap!C17
B20: Subtotal: | C20: =Recap!C18
B21: Profit: | C21: =Recap!C19
B22: Total: | C22: =Recap!C20
B23: Insurance: | C23: =Recap!C21
B25: GRAND TOTAL: | D25: =Recap!C23

Sheet Material Takeoff
B2: MATERIAL TAKEOFF - TPO MEMBRANE
B4: Roof Measurements
B5: Length (ft):
B6: Width (ft):
B7: Waste Factor: | C7: 0.1
B8: Pitch Multiplier: | C8: 1 | D8: (Flat=1.00, 4/12=1.05, 6/12=1.12, 8/12=1.20, 10/12=1.30, 12/12=1.41)
B9: Total Roof Squares: | C9: =IF(AND(C5<>"",C6<>""),((C5*C6)/100)*(1+C7)*C8,0)
B11: Materials Required
B12: Item | C12: Quantity | D12: Unit | E12: Unit Price | F12: Total
B13: TPO Membrane 60mil (10') | C13: 0 | D13: rolls | E13: 485 | F13: =C13*E13
B14: TPO Membrane 80mil (10') | C14: 0 | D14: rolls | E14: 625 | F14: =C14*E14
B15: Polyiso 2.5" (4x8) | C15: =CEILING($C$9*100/32,1) | D15: sheets | E15: 48 | F15: =C15*E15
B16: Polyiso 1.5" tapered | C16: 0 | D16: sheets | E16: 42 | F16: =C16*E16
B17: DensDeck 1/4" (4x8) | C17: =CEILING($C$9*100/32,1) | D17: sheets | E17: 32 | F17: =C17*E17
B18: TPO Bonding Adhesive | C18: =CEILING($C$9/8,1) | D18: 5-gal | E18: 195 | F18: =C18*E18
B19: TPO Seam Tape 6" | C19: 0 | D19: rolls | E19: 145 | F19: =C19*E19
B20: Termination Bar (10') | C20: 0 | D20: pcs | E20: 18 | F20: =C20*E20
B21: Edge Metal 24ga | C21: 0 | D21: 10' pcs | E21: 35 | F21: =C21*E21
B22: TPO Pipe Boots | C22: 4 | D22: each | E22: 65 | F22: =C22*E22
B23: TPO Corners (in/out) | C23: 8 | D23: each | E23: 28 | F23: =C23*E23
B24: Fasteners/Plates (box) | C24: =CEILING($C$9/4,1) | D24: boxes | E24: 125 | F24: =C24*E24
B25: Dumpster/Disposal | C25: 1 | D25: each | E25: 550 | F25: =C25*E25
B26: TOTAL MATERIAL COST: | E26: TOTAL: | F26: =SUM(F13:F25)

Sheet Labor Calculator
B2: LABOR CALCULATOR
B4: LABOR BURDEN (Research-Backed Rates)
B5: Base Hourly Rate: | C5: 28 | D5: (National avg: $21-$33/hr by state)
B6: Workers Comp: | C6: 0.25 | D6: (Roofing avg: 20-30% - high risk trade)
B7: FICA (SS + Medicare): | C7: 0.0765 | D7: (Fixed: 7.65%)
B8: Federal Unemployment: | C8: 0.006 | D8: (FUTA: 0.6%)
B9: State Unemployment: | C9: 0.035 | D9: (SUTA: varies 2-5%)
B10: Benefits/Insurance: | C10: 0.08 | D10: (Health, 401k, etc.)
B11: BURDENED RATE: | C11: =C5*(1+SUM(C6:C10)) | D11: (~45% total burden is industry standard)
B13: CREW COSTS
B14: Crew Size: | C14: 4
B15: Hours/Day: | C15: 8
B16: Daily Crew Cost: | C16: =C11*C14*C15
B18: PRODUCTION RATES (Industry Research)
B19: Task | C19: Rate/Day | D19: Unit | E19: Quantity | F19: Days | G19: Cost
B20: Tear-Off | C20: 15 | D20: SQ | F20: =IF(C20>0,E20/C20,0) | G20: =F20*$C$16
B21: Deck Repair | C21: 100 | D21: SF | F21: =IF(C21>0,E21/C21,0) | G21: =F21*$C$16
B22: Insulation Layer 1 | C22: 20 | D22: SQ | F22: =IF(C22>0,E22/C22,0) | G22: =F22*$C$16
B23: Insulation Layer 2 | C23: 18 | D23: SQ | F23: =IF(C23>0,E23/C23,0) | G23: =F23*$C$16
B24: Cover Board | C24: 18 | D24: SQ | F24: =IF(C24>0,E24/C24,0) | G24: =F24*$C$16
B25: TPO Membrane | C25: 8 | D25: SQ | F25: =IF(C25>0,E25/C25,0) | G25: =F25*$C$16
B26: Seam Welding | C26: 500 | D26: LF | F26: =IF(C26>0,E26/C26,0) | G26: =F26*$C$16
B27: Flashings/Boots | C27: 6 | D27: EA | F27: =IF(C27>0,E27/C27,0) | G27: =F27*$C$16
B28: Edge Metal | C28: 120 | D28: LF | F28: =IF(C28>0,E28/C28,0) | G28: =F28*$C$16
B29: Final Cleanup | C29: 1 | D29: JOB | F29: =IF(C29>0,E29/C29,0) | G29: =F29*$C$16
E30: TOTAL: | F30: =SUM(F20:F29) | G30: =SUM(G20:G29)

Sheet Recap
B2: ESTIMATE RECAP
B3: Professional cost breakdown (Estimating Edge format)
B5: RATES (Edit these)
B6: Material Tax Rate: | C6: 0.075 | D6: (Sales tax - varies by state: 0-10%)
B7: Labor Burden Rate: | C7: 0.45 | D7: (Already in Labor Calc - set to 0 if using)
B8: Profit Margin: | C8: 0.2 | D8: (Industry avg: 15-25% on subtotal)
B9: Insurance Rate: | C9: 0.02 | D9: (GL on total: 1.5-3%)
B11: ESTIMATE BREAKDOWN
B12: Material | C12: ='Material Takeoff'!F26
B13: Material Tax | C13: =C12*C6
B14: Labor + Burden | C14: ='Labor Calculator'!G30
B15: Subcontractors/Equipment | C15: 0
B16: Subtotal | C16: =SUM(C12:C15)
B17: Profit | C17: =C16*C8
B18: Total | C18: =C16+C17
B19: Insurance | C19: =C18*C9
B21: Grand Total | C21: =C18+C19
B23: REFERENCE
B24: Base Materials: | C24: =C12
B25: Base Labor: | C25: ='Labor Calculator'!G30
B26: Profit %: | C26: =C8
B27: Profit $: | C27: =C17
B28: Cost per Square: | C28: =C21/'Material Takeoff'!C9

Sheet Proposal
B2: YOUR COMPANY NAME
B3: Address | Phone | Email | License#
D4: Powered by MC2 Estimating Tools
B6: ROOFING PROPOSAL
B8: PREPARED FOR: | D8: DATE: | E8: =Dashboard!C9
B9: =Dashboard!C6 | D9: PROPOSAL #:
B10: =Dashboard!C4
B12: SCOPE OF WORK
B13: • Remove existing roofing system to structural deck
B14: • Inspect and repair roof deck as needed
B15: • Install tapered polyiso insulation for positive drainage
B16: • Install polyiso cover insulation to achieve R-30
B17: • Install 1/4" DensDeck cover board
B18: • Install 60-mil TPO membrane (fully adhered)
B19: • Heat-weld all seams with 100% seam inspection
B20: • Install pre-fabricated TPO pipe boots and corners
B21: • Install new 24ga edge metal with TPO cover
B22: • Complete debris removal and final inspection
B24: INVESTMENT BREAKDOWN
B25: Materials: | E25: =Recap!C12
B26: Material Tax: | E26: =Recap!C13
B27: Labor: | E27: =Recap!C14
B28: Subtotal: | E28: =Recap!C16
B29: Insurance: | E29: =Recap!C19
B30: TOTAL INVESTMENT: | E30: =Recap!C21
B32: TERMS & CONDITIONS
B33: • 50% deposit required to schedule work
B34: • Final payment due upon completion
B35: • Proposal valid for 30 days
B36: • Warranty: 10 years workmanship, manufacturer warranty on materials
B39: Customer Signature: _________________________________
B40: Date: _________________

Sheet Price List
B2: MATERIAL PRICE LIST
B3: Update prices here - link to Material Takeoff
B5: Material | C5: Unit | D5: Price | E5: Updated
B6: TPO Membrane 60mil (10') | C6: rolls | D6: 485
B7: TPO Membrane 80mil (10') | C7: rolls | D7: 625
B8: Polyiso 2.5" (4x8) | C8: sheets | D8: 48
B9: Polyiso 1.5" tapered | C9: sheets | D9: 42
B10: DensDeck 1/4" (4x8) | C10: sheets | D10: 32
B11: TPO Bonding Adhesive | C11: 5-gal | D11: 195
B12: TPO Seam Tape 6" | C12: rolls | D12: 145
B13: Termination Bar (10') | C13: pcs | D13: 18
B14: Edge Metal 24ga | C14: 10' pcs | D14: 35
B15: TPO Pipe Boots | C15: each | D15: 65
B16: TPO Corners (in/out) | C16: each | D16: 28
B17: Fasteners/Plates (box) | C17: boxes | D17: 125
B18: Dumpster/Disposal | C18: each | D18: 550
