Workbook

Sheet Dashboard
A1: ROOFING ESTIMATE SUMMARY
A3: PROJECT INFORMATION
A4: Customer Name:
A5: Address:
A6: Phone:
A7: Email:
A8: Estimate Date:
A9: Job Number:
A11: ESTIMATE SUMMARY
A12: Total Roof Area (SQ) | B12: =Material_Takeoff!B8
A13: Material | B13: =Recap!C11
A14: Material Tax | B14: =Recap!C12
A15: Labor + Overburden | B15: =Recap!C13
A16: Subcontractors/Equipment | B16: =Recap!C14
A17: Subtotal | B17: =Recap!C15
A18: Profit | B18: =Recap!C16
A19: Total | B19: =Recap!C17
A20: Insurance | B20: =Recap!C18
A21: GRAND TOTAL | B21: =Recap!C19

Sheet Material_Takeoff
A1: Spray Foam Insulation - Material Takeoff
A3: ROOF MEASUREMENTS
A4: Roof Length (ft) | B4: 0
A5: Roof Width (ft) | B5: 0
A6: Waste Factor | B6: 0.1
A7: Pitch Multiplier | B7: 1.12
A8: Total Squares | B8: =(B4*B5*(1+B6)*B7)/100
A10: Item | B10: Quantity | C10: Unit | D10: Unit Price | E10: Total Cost
A11: TEAR-OFF & DISPOSAL
A12: Surface Prep / Cleaning | C12: LS | D12: 200 | E12: =B12*D12
A14: UNDERLAYMENT & ICE SHIELD
A15: Primer/Adhesion Promoter | C15: 5Gal | D15: 65 | E15: =B15*D15
A17: FIELD MATERIALS
A18: Spray Foam Kit (lg) | C18: Kit | D18: 800 | E18: =B18*D18
A19: Spray Foam Kit (sm) | C19: Kit | D19: 650 | E19: =B19*D19
A20: Elastomeric Coating | C20: 5Gal | D20: 120 | E20: =B20*D20
A22: EDGE METAL
A23: Edge Termination | C23: LF | D23: 3 | E23: =B23*D23
A25: FLASHING
A26: Flashing Sealant | C26: Tube | D26: 8 | E26: =B26*D26
A27: Pipe Boot Seal | C27: EA | D27: 15 | E27: =B27*D27
A29: VENTILATION
A30: N/A - Sealed System | C30: EA | D30: 0 | E30: =B30*D30
A32: RIDGE & HIP
A33: Foam Build-up at Ridge | C33: LF | D33: 2 | E33: =B33*D33
A35: MISCELLANEOUS
A36: Spray Gun Rental | C36: Day | D36: 150 | E36: =B36*D36
A37: Protective Suits | C37: EA | D37: 8 | E37: =B37*D37
A38: Respirators | C38: EA | D38: 35 | E38: =B38*D38
A39: Plastic Sheeting | C39: Roll | D39: 25 | E39: =B39*D39
A41: TOTAL MATERIAL COST | E41: =E12+E15+E18+E19+E20+E23+E26+E27+E30+E33+E36+E37+E38+E39

Sheet Labor_Calculator
A1: Spray Foam Insulation - Labor Calculator
A3: LABOR RATES
A4: Crew Size | B4: 4
A5: Hourly Rate per Person | B5: 40
A6: Hours per Day | B6: 8
A8: Item / Description | B8: Hours | C8: Total Cost
A9: Tear-off & Debris Removal | C9: =B9*B4*B5
A10: Deck Inspection & Repair | C10: =B10*B4*B5
A11: Underlayment & Ice Shield | C11: =B11*B4*B5
A12: Field Install | C12: =B12*B4*B5
A13: Edge Metal Install | C13: =B13*B4*B5
A14: Flashing Install | C14: =B14*B4*B5
A15: Pipe Boot & Penetration Install | C15: =B15*B4*B5
A16: Ventilation Install | C16: =B16*B4*B5
A17: Ridge & Hip Install | C17: =B17*B4*B5
A18: Cleanup & Final Inspection | C18: =B18*B4*B5
A20: TOTAL LABOR COST | C20: =C9+C10+C11+C12+C13+C14+C15+C16+C17+C18

Sheet Recap
A1: ESTIMATE RECAP
A2: Professional cost breakdown
A4: RATES (edit these)
A5: Material Tax Rate | B5: 0.075
A6: Labor Overburden Rate | B6: 0.25
A7: Profit Margin | B7: 0.25
A8: Insurance Rate | B8: 0.02
A10: ESTIMATE BREAKDOWN
A11: Material | C11: =Material_Takeoff!E41
A12: Material Tax | C12: =C11*B5
A13: Labor + Overburden | C13: =Labor_Calculator!C20*(1+B6)
A14: Subcontractors/Equipment | C14: 0
A15: Subtotal | C15: =SUM(C11:C14)
A16: Profit | C16: =C15*B7
A17: Total | C17: =C15+C16
A18: Insurance | C18: =C17*B8
A19: GRAND TOTAL | C19: =C17+C18

Sheet Proposal
A1: YOUR COMPANY NAME
A2: Address | Phone | Email | License#
A3: Powered by MC2 Estimating Tools
A5: Spray Foam Insulation ROOFING PROPOSAL
A7: PREPARED FOR:
A8: DATE:
A9: PROPOSAL #:
A11: SCOPE OF WORK
A12: 1. Protect surrounding areas
A13: 2. Apply spray foam insulation
A14: 3. Apply elastomeric coating system
A15: 4. Trim excess foam at edges
... A19: INVESTMENT BREAKDOWN
A20: Material + Tax | D20: =Recap!C11+Recap!C12
A21: Labor | D21: =Recap!C13
A22: TOTAL INVESTMENT | D22: =Recap!C19
A24: TERMS & CONDITIONS
A25: 50% deposit, balance on completion
A26: Estimate valid for 30 days
A28: WARRANTY
A29: Workmanship warranty: __ years
A30: Manufacturer warranty: per specs
A32: ACCEPTANCE
A33: Customer Signature: | C33: ____________
A34: Date: | C34: ____________
A35: Contractor Signature: | C35: ____________

Sheet Price_List
A1: Spray Foam Insulation - Price List
A2: Edit prices for your market
A4: Item | B4: Unit | C4: Price
A5: TEAR-OFF & DISPOSAL
A6: Surface Prep / Cleaning | B6: LS | C6: 200
A8: UNDERLAYMENT & ICE SHIELD
A9: Primer/Adhesion Promoter | B9: 5Gal | C9: 65
A11: FIELD MATERIALS
A12: Spray Foam Kit (lg) | B12: Kit | C12: 800
A13: Spray Foam Kit (sm) | B13: Kit | C13: 650
A14: Elastomeric Coating | B14: 5Gal | C14: 120
A16: EDGE METAL
A17: Edge Termination | B17: LF | C17: 3
A19: FLASHING
A20: Flashing Sealant | B20: Tube | C20: 8
A21: Pipe Boot Seal | B21: EA | C21: 15
A23: VENTILATION
A24: N/A - Sealed System | B24: EA | C24: 0
A26: RIDGE & HIP
A27: Foam Build-up at Ridge | B27: LF | C27: 2
A29: MISCELLANEOUS
A30: Spray Gun Rental | B30: Day | C30: 150
A31: Protective Suits | B31: EA | C31: 8
A32: Respirators | B32: EA | C32: 35
A33: Plastic Sheeting | B33: Roll | C33: 25
A35: LABOR
A36: Hourly Rate per Person | B36: HR | C36: 40
